Workbook

Sheet Summary
A1: Inventory Risk Analysis: Adventure Works (sample data)
A2: All figures are formulas over the Data sheet. Change Assumptions to test other thresholds.
A4: KPI | B4: Value | D4: By category
A5: Stock lines | B5: =COUNTA(Data!$C$2:$C$151) -> 150 | D5: Category | E5: Supplier | F5: Lines | G5: Stock value | H5: Share of value | I5: Discontinued | J5: Active, no reorder level
A6: Units in stock | B6: =SUM(Data!$F$2:$F$151) -> 56920 | D6: Frames | E6: =INDEX(Data!$D$2:$D$151,MATCH(D6,Data!$A$2:$A$151,0)) -> Imortadores Neptuno | F6: =COUNTIF(Data!$A$2:$A$151,D6) -> 74 | G6: =SUMIFS(Data!$J$2:$J$151,Data!$A$2:$A$151,D6) -> 643920 | H6: =G6/$B$7 -> 0.46920736 | I6: =COUNTIFS(Data!$A$2:$A$151,D6,Data!$I$2:$I$151,"Yes") -> 4 | J6: =COUNTIFS(Data!$A$2:$A$151,D6,Data!$L$2:$L$151,"No reorder level") -> 14
A7: Inventory value | B7: =SUM(Data!$J$2:$J$151) -> 1372357 | D7: Tyres | E7: =INDEX(Data!$D$2:$D$151,MATCH(D7,Data!$A$2:$A$151,0)) -> Tyresaz | F7: =COUNTIF(Data!$A$2:$A$151,D7) -> 34 | G7: =SUMIFS(Data!$J$2:$J$151,Data!$A$2:$A$151,D7) -> 331194 | H7: =G7/$B$7 -> 0.24133225 | I7: =COUNTIFS(Data!$A$2:$A$151,D7,Data!$I$2:$I$151,"Yes") -> 2 | J7: =COUNTIFS(Data!$A$2:$A$151,D7,Data!$L$2:$L$151,"No reorder level") -> 8
A8: Active lines (not discontinued) | B8: =COUNTIF(Data!$I$2:$I$151,"No") -> 134 | D8: Gear Components | E8: =INDEX(Data!$D$2:$D$151,MATCH(D8,Data!$A$2:$A$151,0)) -> Z123 | F8: =COUNTIF(Data!$A$2:$A$151,D8) -> 20 | G8: =SUMIFS(Data!$J$2:$J$151,Data!$A$2:$A$151,D8) -> 225424 | H8: =G8/$B$7 -> 0.16426047 | I8: =COUNTIFS(Data!$A$2:$A$151,D8,Data!$I$2:$I$151,"Yes") -> 0 | J8: =COUNTIFS(Data!$A$2:$A$151,D8,Data!$L$2:$L$151,"No reorder level") -> 10
A9: Active lines with no reorder level | B9: =COUNTIF(Data!$L$2:$L$151,"No reorder level") -> 32 | D9: Saddles | E9: =INDEX(Data!$D$2:$D$151,MATCH(D9,Data!$A$2:$A$151,0)) -> Sadleab | F9: =COUNTIF(Data!$A$2:$A$151,D9) -> 12 | G9: =SUMIFS(Data!$J$2:$J$151,Data!$A$2:$A$151,D9) -> 114589 | H9: =G9/$B$7 -> 0.083497953 | I9: =COUNTIFS(Data!$A$2:$A$151,D9,Data!$I$2:$I$151,"Yes") -> 8 | J9: =COUNTIFS(Data!$A$2:$A$151,D9,Data!$L$2:$L$151,"No reorder level") -> 0
A10: value held | B10: =SUMIFS(Data!$J$2:$J$151,Data!$L$2:$L$151,"No reorder level") -> 454786 | D10: Brake System | E10: =INDEX(Data!$D$2:$D$151,MATCH(D10,Data!$A$2:$A$151,0)) -> Cyclesaz | F10: =COUNTIF(Data!$A$2:$A$151,D10) -> 10 | G10: =SUMIFS(Data!$J$2:$J$151,Data!$A$2:$A$151,D10) -> 57230 | H10: =G10/$B$7 -> 0.041701977 | I10: =COUNTIFS(Data!$A$2:$A$151,D10,Data!$I$2:$I$151,"Yes") -> 2 | J10: =COUNTIFS(Data!$A$2:$A$151,D10,Data!$L$2:$L$151,"No reorder level") -> 0
A11: Overstock lines (threshold on Assumptions) | B11: =COUNTIF(Data!$L$2:$L$151,"Overstock") -> 48 | D11: Total | F11: =SUM(F6:F10) -> 150 | G11: =SUM(G6:G10) -> 1372357 | H11: =SUM(H6:H10) -> 1 | I11: =SUM(I6:I10) -> 16 | J11: =SUM(J6:J10) -> 32
A12: value held | B12: =SUMIFS(Data!$J$2:$J$151,Data!$L$2:$L$151,"Overstock") -> 526401 | D12: Check: category total equals KPI value | G12: =IF(ROUND(G11-B7,2)=0,"OK","MISMATCH") -> OK
A13: share of inventory value | B13: =B12/B7 -> 0.38357439
A14: Discontinued lines still in stock | B14: =COUNTIF(Data!$L$2:$L$151,"Discontinued - in stock") -> 8
A15: value held | B15: =SUMIFS(Data!$J$2:$J$151,Data!$L$2:$L$151,"Discontinued - in stock") -> 89052
A16: share of inventory value | B16: =B15/B7 -> 0.064889821
A17: Stock-outs (all) | B17: =COUNTIF(Data!$F$2:$F$151,0) -> 10
A18: of which active and not on order | B18: =COUNTIF(Data!$L$2:$L$151,"Stock-out") -> 0
A19: Exact duplicate rows (repeats) | B19: =COUNTIF(Data!$M$2:$M$151,"Repeat") -> 21
A20: value in repeats | B20: =SUMIFS(Data!$J$2:$J$151,Data!$M$2:$M$151,"Repeat") -> 210899
A21: Price outlier lines | B21: =COUNTIF(Data!$N$2:$N$151,"Outlier") -> 8

Sheet Assumptions
A1: Assumptions (change the yellow cells; every sheet recalculates)
A3: Parameter | B3: Value | C3: Note
A4: Overstock threshold (stock ÷ reorder level ≥) | B4: 20 | C4: My choice, not an industry standard. 10, 20 and 30 are compared on the Sensitivity sheet.
A5: Outlier fence multiplier (× IQR above Q3) | B5: 1.5 | C5: Tukey rule.
A6: Value basis | B6: Unit Price × Units In Stock | C6: The file does not say whether Unit Price is cost or selling price. Value is therefore an upper bound if it is a selling price.
A7: Reorder level = 0 | B7: May be deliberate | C7: A level of 0 can mean made-to-order. The Status column calls these 'No reorder level'; confirm the policy before treating them as a gap.
A8: Source | B8: Adventure Works Inventory sample workbook (training file) | C8: Not real company data. Contains no sales or demand, so days of cover and turnover cannot be calculated.
A9: Date Entered | B9: Static snapshot | C9: Original used =TODAY()+n in 48 rows, so dates moved every time the file opened. Cached values are kept for reference only; no date analysis is made.
A10: Removed from source | B10: ProductsA sheet, external link, broken names | C10: ProductsA = same 150 rows reordered + a SUM row (verified). The source also had a link to another file on a personal drive and a broken named range.

Sheet Sensitivity
A1: How robust are the findings? (counts exclude discontinued lines)
A3: Overstock threshold (x reorder level) | B3: Lines | C3: Value held | D3: Share of inventory value
A4: 10 | B4: =COUNTIFS(Data!$K$2:$K$151,">="&A4,Data!$I$2:$I$151,"No") -> 64 | C4: =SUMIFS(Data!$J$2:$J$151,Data!$K$2:$K$151,">="&A4,Data!$I$2:$I$151,"No") -> 723796 | D4: =C4/Summary!$B$7 -> 0.52741087
A5: 20 | B5: =COUNTIFS(Data!$K$2:$K$151,">="&A5,Data!$I$2:$I$151,"No") -> 48 | C5: =SUMIFS(Data!$J$2:$J$151,Data!$K$2:$K$151,">="&A5,Data!$I$2:$I$151,"No") -> 526401 | D5: =C5/Summary!$B$7 -> 0.38357439
A6: 30 | B6: =COUNTIFS(Data!$K$2:$K$151,">="&A6,Data!$I$2:$I$151,"No") -> 34 | C6: =SUMIFS(Data!$J$2:$J$151,Data!$K$2:$K$151,">="&A6,Data!$I$2:$I$151,"No") -> 420706 | D6: =C6/Summary!$B$7 -> 0.30655726
A8: Reading: even at 30x, a large block of capital sits far above its reorder level. The count depends on the threshold, so treat 48 lines as an estimate.
A10: Duplicates: results with and without exact duplicate rows
A11: Metric | B11: With duplicates | C11: Without repeats | D11: Change
A12: Stock lines | B12: =Summary!B5 -> 150 | C12: =B12-COUNTIF(Data!$M$2:$M$151,"Repeat") -> 129 | D12: =C12/B12-1 -> -0.14
A13: Inventory value | B13: =Summary!B7 -> 1372357 | C13: =B13-SUMIFS(Data!$J$2:$J$151,Data!$M$2:$M$151,"Repeat") -> 1161458 | D13: =C13/B13-1 -> -0.15367649
A14: Overstock value | B14: =Summary!B12 -> 526401 | C14: =B14-SUMIFS(Data!$J$2:$J$151,Data!$M$2:$M$151,"Repeat",Data!$L$2:$L$151,"Overstock") -> 467328.5 | D14: =C14/B14-1 -> -0.11221958
A15: Discontinued, in stock, value | B15: =Summary!B15 -> 89052 | C15: =B15-SUMIFS(Data!$J$2:$J$151,Data!$M$2:$M$151,"Repeat",Data!$L$2:$L$151,"Discontinued - in stock") -> 60922 | D15: =C15/B15-1 -> -0.31588285

Sheet Review list
A1: Lines to review first (filter the Data sheet by Status for the full list)
A3: Largest overstock lines | H3: Row numbers point at the Data sheet. The selection was made in Python (build_data.py logic); the displayed values are live formulas.
A4: Data row | B4: Category | C4: Product | D4: Stock | E4: Reorder level | F4: Value
A5: 15 | B5: =INDEX(Data!$A:$A,$A5) -> Frames | C5: =INDEX(Data!$C:$C,$A5) -> A2Mountain | D5: =INDEX(Data!$F:$F,$A5) -> 1130 | E5: =INDEX(Data!$H:$H,$A5) -> 25 | F5: =INDEX(Data!$J:$J,$A5) -> 32205
A6: 14 | B6: =INDEX(Data!$A:$A,$A6) -> Frames | C6: =INDEX(Data!$C:$C,$A6) -> Rac325 | D6: =INDEX(Data!$F:$F,$A6) -> 1130 | E6: =INDEX(Data!$H:$H,$A6) -> 25 | F6: =INDEX(Data!$J:$J,$A6) -> 32205
A7: 87 | B7: =INDEX(Data!$A:$A,$A7) -> Saddles | C7: =INDEX(Data!$C:$C,$A7) -> All weather | D7: =INDEX(Data!$F:$F,$A7) -> 1150 | E7: =INDEX(Data!$H:$H,$A7) -> 20 | F7: =INDEX(Data!$J:$J,$A7) -> 27600
A8: 86 | B8: =INDEX(Data!$A:$A,$A8) -> Saddles | C8: =INDEX(Data!$C:$C,$A8) -> Narrow | D8: =INDEX(Data!$F:$F,$A8) -> 1150 | E8: =INDEX(Data!$H:$H,$A8) -> 20 | F8: =INDEX(Data!$J:$J,$A8) -> 27600
A9: 98 | B9: =INDEX(Data!$A:$A,$A9) -> Tyres | C9: =INDEX(Data!$C:$C,$A9) -> Tubular | D9: =INDEX(Data!$F:$F,$A9) -> 1230 | E9: =INDEX(Data!$H:$H,$A9) -> 30 | F9: =INDEX(Data!$J:$J,$A9) -> 22632
A10: 99 | B10: =INDEX(Data!$A:$A,$A10) -> Tyres | C10: =INDEX(Data!$C:$C,$A10) -> Tubeless | D10: =INDEX(Data!$F:$F,$A10) -> 1230 | E10: =INDEX(Data!$H:$H,$A10) -> 30 | F10: =INDEX(Data!$J:$J,$A10) -> 22632
A11: 100 | B11: =INDEX(Data!$A:$A,$A11) -> Tyres | C11: =INDEX(Data!$C:$C,$A11) -> Tubeless | D11: =INDEX(Data!$F:$F,$A11) -> 1120 | E11: =INDEX(Data!$H:$H,$A11) -> 20 | F11: =INDEX(Data!$J:$J,$A11) -> 21280
A12: 101 | B12: =INDEX(Data!$A:$A,$A12) -> Tyres | C12: =INDEX(Data!$C:$C,$A12) -> Tubeless | D12: =INDEX(Data!$F:$F,$A12) -> 1120 | E12: =INDEX(Data!$H:$H,$A12) -> 20 | F12: =INDEX(Data!$J:$J,$A12) -> 21280
A13: 17 | B13: =INDEX(Data!$A:$A,$A13) -> Frames | C13: =INDEX(Data!$C:$C,$A13) -> 14City | D13: =INDEX(Data!$F:$F,$A13) -> 1110 | E13: =INDEX(Data!$H:$H,$A13) -> 15 | F13: =INDEX(Data!$J:$J,$A13) -> 15540
A14: 16 | B14: =INDEX(Data!$A:$A,$A14) -> Frames | C14: =INDEX(Data!$C:$C,$A14) -> Rac564 | D14: =INDEX(Data!$F:$F,$A14) -> 1110 | E14: =INDEX(Data!$H:$H,$A14) -> 15 | F14: =INDEX(Data!$J:$J,$A14) -> 15540
A16: Largest discontinued lines still in stock
A17: Data row | B17: Category | C17: Product | D17: Stock | E17: Reorder level | F17: Value
A18: 89 | B18: =INDEX(Data!$A:$A,$A18) -> Saddles | C18: =INDEX(Data!$C:$C,$A18) -> All weather | D18: =INDEX(Data!$F:$F,$A18) -> 290 | E18: =INDEX(Data!$H:$H,$A18) -> 0 | F18: =INDEX(Data!$J:$J,$A18) -> 28130
A19: 88 | B19: =INDEX(Data!$A:$A,$A19) -> Saddles | C19: =INDEX(Data!$C:$C,$A19) -> All weather | D19: =INDEX(Data!$F:$F,$A19) -> 290 | E19: =INDEX(Data!$H:$H,$A19) -> 0 | F19: =INDEX(Data!$J:$J,$A19) -> 28130
A20: 117 | B20: =INDEX(Data!$A:$A,$A20) -> Tyres | C20: =INDEX(Data!$C:$C,$A20) -> Tubeless | D20: =INDEX(Data!$F:$F,$A20) -> 260 | E20: =INDEX(Data!$H:$H,$A20) -> 0 | F20: =INDEX(Data!$J:$J,$A20) -> 11856
A21: 116 | B21: =INDEX(Data!$A:$A,$A21) -> Tyres | C21: =INDEX(Data!$C:$C,$A21) -> Tubular | D21: =INDEX(Data!$F:$F,$A21) -> 260 | E21: =INDEX(Data!$H:$H,$A21) -> 0 | F21: =INDEX(Data!$J:$J,$A21) -> 11856
A22: 7 | B22: =INDEX(Data!$A:$A,$A22) -> Brake System | C22: =INDEX(Data!$C:$C,$A22) -> Levers | D22: =INDEX(Data!$F:$F,$A22) -> 260 | E22: =INDEX(Data!$H:$H,$A22) -> 0 | F22: =INDEX(Data!$J:$J,$A22) -> 3640
A23: 6 | B23: =INDEX(Data!$A:$A,$A23) -> Brake System | C23: =INDEX(Data!$C:$C,$A23) -> Pads | D23: =INDEX(Data!$F:$F,$A23) -> 260 | E23: =INDEX(Data!$H:$H,$A23) -> 0 | F23: =INDEX(Data!$J:$J,$A23) -> 3640
A24: 55 | B24: =INDEX(Data!$A:$A,$A24) -> Frames | C24: =INDEX(Data!$C:$C,$A24) -> 14City | D24: =INDEX(Data!$F:$F,$A24) -> 200 | E24: =INDEX(Data!$H:$H,$A24) -> 0 | F24: =INDEX(Data!$J:$J,$A24) -> 900
A25: 54 | B25: =INDEX(Data!$A:$A,$A25) -> Frames | C25: =INDEX(Data!$C:$C,$A25) -> Rac564 | D25: =INDEX(Data!$F:$F,$A25) -> 200 | E25: =INDEX(Data!$H:$H,$A25) -> 0 | F25: =INDEX(Data!$J:$J,$A25) -> 900
A27: Largest active lines with no reorder level
A28: Data row | B28: Category | C28: Product | D28: Stock | E28: Reorder level | F28: Value
A29: 136 | B29: =INDEX(Data!$A:$A,$A29) -> Gear Components | C29: =INDEX(Data!$C:$C,$A29) -> Chain | D29: =INDEX(Data!$F:$F,$A29) -> 790 | E29: =INDEX(Data!$H:$H,$A29) -> 0 | F29: =INDEX(Data!$J:$J,$A29) -> 43450
A30: 137 | B30: =INDEX(Data!$A:$A,$A30) -> Gear Components | C30: =INDEX(Data!$C:$C,$A30) -> belt drives | D30: =INDEX(Data!$F:$F,$A30) -> 790 | E30: =INDEX(Data!$H:$H,$A30) -> 0 | F30: =INDEX(Data!$J:$J,$A30) -> 43450
A31: 135 | B31: =INDEX(Data!$A:$A,$A31) -> Gear Components | C31: =INDEX(Data!$C:$C,$A31) -> derailleurs | D31: =INDEX(Data!$F:$F,$A31) -> 860 | E31: =INDEX(Data!$H:$H,$A31) -> 0 | F31: =INDEX(Data!$J:$J,$A31) -> 32680
A32: 134 | B32: =INDEX(Data!$A:$A,$A32) -> Gear Components | C32: =INDEX(Data!$C:$C,$A32) -> derailleurs | D32: =INDEX(Data!$F:$F,$A32) -> 860 | E32: =INDEX(Data!$H:$H,$A32) -> 0 | F32: =INDEX(Data!$J:$J,$A32) -> 32680
A33: 35 | B33: =INDEX(Data!$A:$A,$A33) -> Frames | C33: =INDEX(Data!$C:$C,$A33) -> A2Mountain | D33: =INDEX(Data!$F:$F,$A33) -> 400 | E33: =INDEX(Data!$H:$H,$A33) -> 0 | F33: =INDEX(Data!$J:$J,$A33) -> 32400
A34: 34 | B34: =INDEX(Data!$A:$A,$A34) -> Frames | C34: =INDEX(Data!$C:$C,$A34) -> Zelectric | D34: =INDEX(Data!$F:$F,$A34) -> 400 | E34: =INDEX(Data!$H:$H,$A34) -> 0 | F34: =INDEX(Data!$J:$J,$A34) -> 32400
A35: 111 | B35: =INDEX(Data!$A:$A,$A35) -> Tyres | C35: =INDEX(Data!$C:$C,$A35) -> Clincher | D35: =INDEX(Data!$F:$F,$A35) -> 420 | E35: =INDEX(Data!$H:$H,$A35) -> 0 | F35: =INDEX(Data!$J:$J,$A35) -> 26250
A36: 110 | B36: =INDEX(Data!$A:$A,$A36) -> Tyres | C36: =INDEX(Data!$C:$C,$A36) -> Tubular | D36: =INDEX(Data!$F:$F,$A36) -> 420 | E36: =INDEX(Data!$H:$H,$A36) -> 0 | F36: =INDEX(Data!$J:$J,$A36) -> 26250
A37: 20 | B37: =INDEX(Data!$A:$A,$A37) -> Frames | C37: =INDEX(Data!$C:$C,$A37) -> Rac564 | D37: =INDEX(Data!$F:$F,$A37) -> 760 | E37: =INDEX(Data!$H:$H,$A37) -> 0 | F37: =INDEX(Data!$J:$J,$A37) -> 15998
A38: 21 | B38: =INDEX(Data!$A:$A,$A38) -> Frames | C38: =INDEX(Data!$C:$C,$A38) -> 14City | D38: =INDEX(Data!$F:$F,$A38) -> 760 | E38: =INDEX(Data!$H:$H,$A38) -> 0 | F38: =INDEX(Data!$J:$J,$A38) -> 15998

Sheet Data
A1: Category | B1: Date Entered (snapshot) | C1: Product Name | D1: Supplier | E1: Unit Price | F1: Units In Stock | G1: Units On Order | H1: Reorder Level | I1: Discontinued | J1: Stock Value | K1: Cover (x reorder) | L1: Status | M1: Exact Duplicate | N1: Price Outlier
A2: Brake System | B2: 46338 | C2: Levers | D2: Cyclesaz | E2: 7 | F2: 380 | G2: 0 | H2: 25 | I2: No | J2: =E2*F2 -> 2660 | K2: =IF(H2>0,F2/H2,"") -> 15.2 | L2: =IF(I2="Yes",IF(F2>0,"Discontinued - in stock","Discontinued"),IF(F2=0,IF(G2>0,"Stock-out - on order","Stock-out"),IF(H2=0,"No reorder level",IF(K2>=Assumptions!$B$4,"Overstock","OK")))) -> OK | M2: =IF(COUNTIFS($A$2:$A$151,A2,$B$2:$B$151,B2,$C$2:$C$151,C2,$D$2:$D$151,D2,$E$2:$E$151,E2,$F$2:$F$151,F2,$G$2:$G$151,G2,$H$2:$H$151,H2,$I$2:$I$151,I2)>1,IF(COUNTIFS($A$2:A2,A2,$B$2:B2,B2,$C$2:C2,C2,$D$2:D2,D2,$E$2:E2,E2,$F$2:F2,F2,$G$2:G2,G2,$H$2:H2,H2,$I$2:I2,I2)>1,"Repeat","First"),"") | N2: =IF(E2>QUARTILE($E$2:$E$151,3)+Assumptions!$B$5*(QUARTILE($E$2:$E$151,3)-QUARTILE($E$2:$E$151,1)),"Outlier","")
A3: Brake System | B3: 46338 | C3: Cables | D3: Cyclesaz | E3: 7 | F3: 380 | G3: 0 | H3: 25 | I3: No | J3: =E3*F3 -> 2660 | K3: =IF(H3>0,F3/H3,"") -> 15.2 | L3: =IF(I3="Yes",IF(F3>0,"Discontinued - in stock","Discontinued"),IF(F3=0,IF(G3>0,"Stock-out - on order","Stock-out"),IF(H3=0,"No reorder level",IF(K3>=Assumptions!$B$4,"Overstock","OK")))) -> OK | M3: =IF(COUNTIFS($A$2:$A$151,A3,$B$2:$B$151,B3,$C$2:$C$151,C3,$D$2:$D$151,D3,$E$2:$E$151,E3,$F$2:$F$151,F3,$G$2:$G$151,G3,$H$2:$H$151,H3,$I$2:$I$151,I3)>1,IF(COUNTIFS($A$2:A3,A3,$B$2:B3,B3,$C$2:C3,C3,$D$2:D3,D3,$E$2:E3,E3,$F$2:F3,F3,$G$2:G3,G3,$H$2:H3,H3,$I$2:I3,I3)>1,"Repeat","First"),"") | N3: =IF(E3>QUARTILE($E$2:$E$151,3)+Assumptions!$B$5*(QUARTILE($E$2:$E$151,3)-QUARTILE($E$2:$E$151,1)),"Outlier","")
A4: Brake System | B4: 44571 | C4: Pads | D4: Cyclesaz | E4: 19.5 | F4: 360 | G4: 0 | H4: 20 | I4: No | J4: =E4*F4 -> 7020 | K4: =IF(H4>0,F4/H4,"") -> 18 | L4: =IF(I4="Yes",IF(F4>0,"Discontinued - in stock","Discontinued"),IF(F4=0,IF(G4>0,"Stock-out - on order","Stock-out"),IF(H4=0,"No reorder level",IF(K4>=Assumptions!$B$4,"Overstock","OK")))) -> OK | M4: =IF(COUNTIFS($A$2:$A$151,A4,$B$2:$B$151,B4,$C$2:$C$151,C4,$D$2:$D$151,D4,$E$2:$E$151,E4,$F$2:$F$151,F4,$G$2:$G$151,G4,$H$2:$H$151,H4,$I$2:$I$151,I4)>1,IF(COUNTIFS($A$2:A4,A4,$B$2:B4,B4,$C$2:C4,C4,$D$2:D4,D4,$E$2:E4,E4,$F$2:F4,F4,$G$2:G4,G4,$H$2:H4,H4,$I$2:I4,I4)>1,"Repeat","First"),"") | N4: =IF(E4>QUARTILE($E$2:$E$151,3)+Assumptions!$B$5*(QUARTILE($E$2:$E$151,3)-QUARTILE($E$2:$E$151,1)),"Outlier","")
A5: Brake System | B5: 44571 | C5: Levers | D5: Cyclesaz | E5: 19.5 | F5: 360 | G5: 0 | H5: 20 | I5: No | J5: =E5*F5 -> 7020 | K5: =IF(H5>0,F5/H5,"") -> 18 | L5: =IF(I5="Yes",IF(F5>0,"Discontinued - in stock","Discontinued"),IF(F5=0,IF(G5>0,"Stock-out - on order","Stock-out"),IF(H5=0,"No reorder level",IF(K5>=Assumptions!$B$4,"Overstock","OK")))) -> OK | M5: =IF(COUNTIFS($A$2:$A$151,A5,$B$2:$B$151,B5,$C$2:$C$151,C5,$D$2:$D$151,D5,$E$2:$E$151,E5,$F$2:$F$151,F5,$G$2:$G$151,G5,$H$2:$H$151,H5,$I$2:$I$151,I5)>1,IF(COUNTIFS($A$2:A5,A5,$B$2:B5,B5,$C$2:C5,C5,$D$2:D5,D5,$E$2:E5,E5,$F$2:F5,F5,$G$2:G5,G5,$H$2:H5,H5,$I$2:I5,I5)>1,"Repeat","First"),"") | N5: =IF(E5>QUARTILE($E$2:$E$151,3)+Assumptions!$B$5*(QUARTILE($E$2:$E$151,3)-QUARTILE($E$2:$E$151,1)),"Outlier","")
A6: Brake System | B6: 44549 | C6: Pads | D6: Cyclesaz | E6: 14 | F6: 260 | G6: 0 | H6: 0 | I6: Yes | J6: =E6*F6 -> 3640 | K6: =IF(H6>0,F6/H6,"") | L6: =IF(I6="Yes",IF(F6>0,"Discontinued - in stock","Discontinued"),IF(F6=0,IF(G6>0,"Stock-out - on order","Stock-out"),IF(H6=0,"No reorder level",IF(K6>=Assumptions!$B$4,"Overstock","OK")))) -> Discontinued - in stock | M6: =IF(COUNTIFS($A$2:$A$151,A6,$B$2:$B$151,B6,$C$2:$C$151,C6,$D$2:$D$151,D6,$E$2:$E$151,E6,$F$2:$F$151,F6,$G$2:$G$151,G6,$H$2:$H$151,H6,$I$2:$I$151,I6)>1,IF(COUNTIFS($A$2:A6,A6,$B$2:B6,B6,$C$2:C6,C6,$D$2:D6,D6,$E$2:E6,E6,$F$2:F6,F6,$G$2:G6,G6,$H$2:H6,H6,$I$2:I6,I6)>1,"Repeat","First"),"") | N6: =IF(E6>QUARTILE($E$2:$E$151,3)+Assumptions!$B$5*(QUARTILE($E$2:$E$151,3)-QUARTILE($E$2:$E$151,1)),"Outlier","")
A7: Brake System | B7: 44549 | C7: Levers | D7: Cyclesaz | E7: 14 | F7: 260 | G7: 0 | H7: 0 | I7: Yes | J7: =E7*F7 -> 3640 | K7: =IF(H7>0,F7/H7,"") | L7: =IF(I7="Yes",IF(F7>0,"Discontinued - in stock","Discontinued"),IF(F7=0,IF(G7>0,"Stock-out - on order","Stock-out"),IF(H7=0,"No reorder level",IF(K7>=Assumptions!$B$4,"Overstock","OK")))) -> Discontinued - in stock | M7: =IF(COUNTIFS($A$2:$A$151,A7,$B$2:$B$151,B7,$C$2:$C$151,C7,$D$2:$D$151,D7,$E$2:$E$151,E7,$F$2:$F$151,F7,$G$2:$G$151,G7,$H$2:$H$151,H7,$I$2:$I$151,I7)>1,IF(COUNTIFS($A$2:A7,A7,$B$2:B7,B7,$C$2:C7,C7,$D$2:D7,D7,$E$2:E7,E7,$F$2:F7,F7,$G$2:G7,G7,$H$2:H7,H7,$I$2:I7,I7)>1,"Repeat","First"),"") | N7: =IF(E7>QUARTILE($E$2:$E$151,3)+Assumptions!$B$5*(QUARTILE($E$2:$E$151,3)-QUARTILE($E$2:$E$151,1)),"Outlier","")
A8: Brake System | B8: 44581 | C8: Pads | D8: Cyclesaz | E8: 33.25 | F8: 220 | G8: 80 | H8: 30 | I8: No | J8: =E8*F8 -> 7315 | K8: =IF(H8>0,F8/H8,"") -> 7.3333333 | L8: =IF(I8="Yes",IF(F8>0,"Discontinued - in stock","Discontinued"),IF(F8=0,IF(G8>0,"Stock-out - on order","Stock-out"),IF(H8=0,"No reorder level",IF(K8>=Assumptions!$B$4,"Overstock","OK")))) -> OK | M8: =IF(COUNTIFS($A$2:$A$151,A8,$B$2:$B$151,B8,$C$2:$C$151,C8,$D$2:$D$151,D8,$E$2:$E$151,E8,$F$2:$F$151,F8,$G$2:$G$151,G8,$H$2:$H$151,H8,$I$2:$I$151,I8)>1,IF(COUNTIFS($A$2:A8,A8,$B$2:B8,B8,$C$2:C8,C8,$D$2:D8,D8,$E$2:E8,E8,$F$2:F8,F8,$G$2:G8,G8,$H$2:H8,H8,$I$2:I8,I8)>1,"Repeat","First"),"") -> First | N8: =IF(E8>QUARTILE($E$2:$E$151,3)+Assumptions!$B$5*(QUARTILE($E$2:$E$151,3)-QUARTILE($E$2:$E$151,1)),"Outlier","")
A9: Brake System | B9: 44581 | C9: Pads | D9: Cyclesaz | E9: 33.25 | F9: 220 | G9: 80 | H9: 30 | I9: No | J9: =E9*F9 -> 7315 | K9: =IF(H9>0,F9/H9,"") -> 7.3333333 | L9: =IF(I9="Yes",IF(F9>0,"Discontinued - in stock","Discontinued"),IF(F9=0,IF(G9>0,"Stock-out - on order","Stock-out"),IF(H9=0,"No reorder level",IF(K9>=Assumptions!$B$4,"Overstock","OK")))) -> OK | M9: =IF(COUNTIFS($A$2:$A$151,A9,$B$2:$B$151,B9,$C$2:$C$151,C9,$D$2:$D$151,D9,$E$2:$E$151,E9,$F$2:$F$151,F9,$G$2:$G$151,G9,$H$2:$H$151,H9,$I$2:$I$151,I9)>1,IF(COUNTIFS($A$2:A9,A9,$B$2:B9,B9,$C$2:C9,C9,$D$2:D9,D9,$E$2:E9,E9,$F$2:F9,F9,$G$2:G9,G9,$H$2:H9,H9,$I$2:I9,I9)>1,"Repeat","First"),"") -> Repeat | N9: =IF(E9>QUARTILE($E$2:$E$151,3)+Assumptions!$B$5*(QUARTILE($E$2:$E$151,3)-QUARTILE($E$2:$E$151,1)),"Outlier","")
A10: Brake System | B10: 44570 | C10: Levers | D10: Cyclesaz | E10: 38 | F10: 210 | G10: 10 | H10: 30 | I10: No | J10: =E10*F10 -> 7980 | K10: =IF(H10>0,F10/H10,"") -> 7 | L10: =IF(I10="Yes",IF(F10>0,"Discontinued - in stock","Discontinued"),IF(F10=0,IF(G10>0,"Stock-out - on order","Stock-out"),IF(H10=0,"No reorder level",IF(K10>=Assumptions!$B$4,"Overstock","OK")))) -> OK | M10: =IF(COUNTIFS($A$2:$A$151,A10,$B$2:$B$151,B10,$C$2:$C$151,C10,$D$2:$D$151,D10,$E$2:$E$151,E10,$F$2:$F$151,F10,$G$2:$G$151,G10,$H$2:$H$151,H10,$I$2:$I$151,I10)>1,IF(COUNTIFS($A$2:A10,A10,$B$2:B10,B10,$C$2:C10,C10,$D$2:D10,D10,$E$2:E10,E10,$F$2:F10,F10,$G$2:G10,G10,$H$2:H10,H10,$I$2:I10,I10)>1,"Repeat","First"),"") | N10: =IF(E10>QUARTILE($E$2:$E$151,3)+Assumptions!$B$5*(QUARTILE($E$2:$E$151,3)-QUARTILE($E$2:$E$151,1)),"Outlier","")
A11: Brake System | B11: 44570 | C11: Cables | D11: Cyclesaz | E11: 38 | F11: 210 | G11: 10 | H11: 30 | I11: No | J11: =E11*F11 -> 7980 | K11: =IF(H11>0,F11/H11,"") -> 7 | L11: =IF(I11="Yes",IF(F11>0,"Discontinued - in stock","Discontinued"),IF(F11=0,IF(G11>0,"Stock-out - on order","Stock-out"),IF(H11=0,"No reorder level",IF(K11>=Assumptions!$B$4,"Overstock","OK")))) -> OK | M11: =IF(COUNTIFS($A$2:$A$151,A11,$B$2:$B$151,B11,$C$2:$C$151,C11,$D$2:$D$151,D11,$E$2:$E$151,E11,$F$2:$F$151,F11,$G$2:$G$151,G11,$H$2:$H$151,H11,$I$2:$I$151,I11)>1,IF(COUNTIFS($A$2:A11,A11,$B$2:B11,B11,$C$2:C11,C11,$D$2:D11,D11,$E$2:E11,E11,$F$2:F11,F11,$G$2:G11,G11,$H$2:H11,H11,$I$2:I11,I11)>1,"Repeat","First"),"") | N11: =IF(E11>QUARTILE($E$2:$E$151,3)+Assumptions!$B$5*(QUARTILE($E$2:$E$151,3)-QUARTILE($E$2:$E$151,1)),"Outlier","")
A12: Frames | B12: 46298 | C12: Zelectric | D12: Imortadores Neptuno | E12: 7.75 | F12: 1250 | G12: 0 | H12: 25 | I12: No | J12: =E12*F12 -> 9687.5 | K12: =IF(H12>0,F12/H12,"") -> 50 | L12: =IF(I12="Yes",IF(F12>0,"Discontinued - in stock","Discontinued"),IF(F12=0,IF(G12>0,"Stock-out - on order","Stock-out"),IF(H12=0,"No reorder level",IF(K12>=Assumptions!$B$4,"Overstock","OK")))) -> Overstock | M12: =IF(COUNTIFS($A$2:$A$151,A12,$B$2:$B$151,B12,$C$2:$C$151,C12,$D$2:$D$151,D12,$E$2:$E$151,E12,$F$2:$F$151,F12,$G$2:$G$151,G12,$H$2:$H$151,H12,$I$2:$I$151,I12)>1,IF(COUNTIFS($A$2:A12,A12,$B$2:B12,B12,$C$2:C12,C12,$D$2:D12,D12,$E$2:E12,E12,$F$2:F12,F12,$G$2:G12,G12,$H$2:H12,H12,$I$2:I12,I12)>1,"Repeat","First"),"") | N12: =IF(E12>QUARTILE($E$2:$E$151,3)+Assumptions!$B$5*(QUARTILE($E$2:$E$151,3)-QUARTILE($E$2:$E$151,1)),"Outlier","")
A13: Frames | B13: 46298 | C13: 14City | D13: Imortadores Neptuno | E13: 7.75 | F13: 1250 | G13: 0 | H13: 25 | I13: No | J13: =E13*F13 -> 9687.5 | K13: =IF(H13>0,F13/H13,"") -> 50 | L13: =IF(I13="Yes",IF(F13>0,"Discontinued - in stock","Discontinued"),IF(F13=0,IF(G13>0,"Stock-out - on order","Stock-out"),IF(H13=0,"No reorder level",IF(K13>=Assumptions!$B$4,"Overstock","OK")))) -> Overstock | M13: =IF(COUNTIFS($A$2:$A$151,A13,$B$2:$B$151,B13,$C$2:$C$151,C13,$D$2:$D$151,D13,$E$2:$E$151,E13,$F$2:$F$151,F13,$G$2:$G$151,G13,$H$2:$H$151,H13,$I$2:$I$151,I13)>1,IF(COUNTIFS($A$2:A13,A13,$B$2:B13,B13,$C$2:C13,C13,$D$2:D13,D13,$E$2:E13,E13,$F$2:F13,F13,$G$2:G13,G13,$H$2:H13,H13,$I$2:I13,I13)>1,"Repeat","First"),"") | N13: =IF(E13>QUARTILE($E$2:$E$151,3)+Assumptions!$B$5*(QUARTILE($E$2:$E$151,3)-QUARTILE($E$2:$E$151,1)),"Outlier","")
... A151: Gear Components | B151: 44455 | C151: belt drives | D151: Z123 | E151: 12.5 | F151: 0 | G151: 70 | H151: 20 | I151: No | J151: =E151*F151 -> 0 | K151: =IF(H151>0,F151/H151,"") -> 0 | L151: =IF(I151="Yes",IF(F151>0,"Discontinued - in stock","Discontinued"),IF(F151=0,IF(G151>0,"Stock-out - on order","Stock-out"),IF(H151=0,"No reorder level",IF(K151>=Assumptions!$B$4,"Overstock","OK")))) -> Stock-out - on order | M151: =IF(COUNTIFS($A$2:$A$151,A151,$B$2:$B$151,B151,$C$2:$C$151,C151,$D$2:$D$151,D151,$E$2:$E$151,E151,$F$2:$F$151,F151,$G$2:$G$151,G151,$H$2:$H$151,H151,$I$2:$I$151,I151)>1,IF(COUNTIFS($A$2:A151,A151,$B$2:B151,B151,$C$2:C151,C151,$D$2:D151,D151,$E$2:E151,E151,$F$2:F151,F151,$G$2:G151,G151,$H$2:H151,H151,$I$2:I151,I151)>1,"Repeat","First"),"") -> Repeat | N151: =IF(E151>QUARTILE($E$2:$E$151,3)+Assumptions!$B$5*(QUARTILE($E$2:$E$151,3)-QUARTILE($E$2:$E$151,1)),"Outlier","")
